{
  "$schema": "https://ui.shadcn.com/schema/registry-item.json",
  "name": "dashboard-header-10",
  "type": "registry:block",
  "description": "Standalone navigation header with logo, mega menu dropdowns, mobile responsive design, and comprehensive user controls",
  "dependencies": [
    "lucide-react"
  ],
  "registryDependencies": [
    "avatar",
    "badge",
    "button",
    "card",
    "collapsible",
    "dropdown-menu",
    "input",
    "navigation-menu",
    "separator",
    "sheet",
    "tabs"
  ],
  "files": [
    {
      "path": "src/registry/new-york/blocks/dashboard-and-application/dashboard-header/dashboard-header-10/page.tsx",
      "content": "import { ActivityIcon, BellIcon, LanguagesIcon, MenuIcon } from 'lucide-react'\n\nimport { Button } from '@/components/ui/button'\nimport { Card, CardContent } from '@/components/ui/card'\nimport { Avatar, AvatarFallback, AvatarImage } from '@/components/ui/avatar'\nimport {\n  NavigationMenu,\n  NavigationMenuContent,\n  NavigationMenuItem,\n  NavigationMenuLink,\n  NavigationMenuList,\n  NavigationMenuTrigger,\n  navigationMenuTriggerStyle\n} from '@/components/ui/navigation-menu'\n\nimport LogoSvg from '@/assets/svg/logo'\nimport LanguageDropdown from '@/components/shadcn-studio/blocks/dropdown-language'\nimport ActivityDialog from '@/components/shadcn-studio/blocks/dialog-activity'\nimport NotificationDropdown from '@/components/shadcn-studio/blocks/dropdown-notification'\nimport ProfileDropdown from '@/components/shadcn-studio/blocks/dropdown-profile'\nimport MenuDropdown from '@/components/shadcn-studio/blocks/menu-dropdown'\nimport type { NavigationSection } from '@/components/shadcn-studio/blocks/menu-dropdown'\n\nconst navigationData: NavigationSection[] = [\n  {\n    title: 'Components',\n    items: [\n      { title: 'Alert Dialog', href: '#' },\n      { title: 'Hover Card', href: '#' },\n      { title: 'Progress', href: '#' },\n      { title: 'Scroll-area', href: '#' },\n      { title: 'Tabs', href: '#' },\n      { title: 'Tooltip', href: '#' }\n    ]\n  },\n  {\n    title: 'Docs',\n    href: '#'\n  },\n  {\n    title: 'Resources',\n    items: [\n      { title: 'Tutorials', href: '#' },\n      { title: 'References', href: '#' }\n    ]\n  },\n  {\n    title: 'Manage Account',\n    items: [\n      { title: 'Account', href: '#' },\n      { title: 'Preferences', href: '#' },\n      { title: 'Billing', href: '#' },\n      { title: 'Help Center', href: '#' }\n    ]\n  }\n]\n\nconst Header = () => {\n  return (\n    <div className='flex min-h-dvh flex-col'>\n      <header className='bg-card sticky top-0 z-50 border-b'>\n        <div className='mx-auto flex max-w-7xl items-center justify-between gap-8 px-4 py-2 sm:px-6'>\n          <div className='flex items-center gap-4'>\n            <MenuDropdown\n              navigationData={navigationData}\n              trigger={\n                <Button variant='outline' size='icon' className='inline-flex lg:hidden'>\n                  <MenuIcon />\n                  <span className='sr-only'>Menu</span>\n                </Button>\n              }\n            />\n            <a href='#'>\n              <div className='flex items-center'>\n                <LogoSvg className='size-8.5' />\n                <span className='ml-2.5 hidden text-xl font-semibold sm:block'>shadcn/studio</span>\n              </div>\n            </a>\n          </div>\n          <NavigationMenu viewport={false} className='hidden max-w-full lg:block'>\n            <NavigationMenuList className='flex-wrap justify-start'>\n              {navigationData.map(navItem => {\n                if (navItem.href) {\n                  // Root link item\n                  return (\n                    <NavigationMenuItem key={navItem.title}>\n                      <NavigationMenuLink href={navItem.href} className={navigationMenuTriggerStyle()}>\n                        {navItem.title}\n                      </NavigationMenuLink>\n                    </NavigationMenuItem>\n                  )\n                }\n\n                // Section with dropdown\n                return (\n                  <NavigationMenuItem key={navItem.title}>\n                    <NavigationMenuTrigger>{navItem.title}</NavigationMenuTrigger>\n                    <NavigationMenuContent className='data-[motion=from-start]:slide-in-from-left-30! data-[motion=to-start]:slide-out-to-left-30! data-[motion=from-end]:slide-in-from-right-30! data-[motion=to-end]:slide-out-to-right-30! absolute w-auto'>\n                      <ul className='grid w-38 gap-4'>\n                        <li>\n                          {navItem.items?.map(item => (\n                            <NavigationMenuLink key={item.title} href={item.href}>\n                              {item.title}\n                            </NavigationMenuLink>\n                          ))}\n                        </li>\n                      </ul>\n                    </NavigationMenuContent>\n                  </NavigationMenuItem>\n                )\n              })}\n            </NavigationMenuList>\n          </NavigationMenu>\n          <div className='flex items-center gap-6'>\n            <div className='flex items-center gap-1.5'>\n              <LanguageDropdown\n                trigger={\n                  <Button variant='outline' size='icon'>\n                    <LanguagesIcon />\n                  </Button>\n                }\n              />\n              <ActivityDialog\n                trigger={\n                  <Button variant='outline' size='icon'>\n                    <ActivityIcon />\n                  </Button>\n                }\n              />\n              <NotificationDropdown\n                trigger={\n                  <Button variant='outline' size='icon' className='relative'>\n                    <BellIcon />\n                    <span className='bg-destructive absolute -top-0.5 -right-0.5 size-2 rounded-full' />\n                  </Button>\n                }\n              />\n            </div>\n            <ProfileDropdown\n              trigger={\n                <Button variant='ghost' className='h-full rounded-full p-0'>\n                  <Avatar className='size-9.5'>\n                    <AvatarImage src='https://cdn.shadcnstudio.com/ss-assets/avatar/avatar-1.png' />\n                    <AvatarFallback>JD</AvatarFallback>\n                  </Avatar>\n                </Button>\n              }\n            />\n          </div>\n        </div>\n      </header>\n      <main className='mx-auto size-full max-w-7xl flex-1 px-4 py-6 sm:px-6'>\n        <Card className='h-250'>\n          <CardContent className='h-full'>\n            <div className='border-card-foreground/10 h-full rounded-md border bg-[repeating-linear-gradient(45deg,color-mix(in_oklab,var(--card-foreground)10%,transparent),color-mix(in_oklab,var(--card-foreground)10%,transparent)_1px,var(--card)_2px,var(--card)_15px)]' />\n          </CardContent>\n        </Card>\n      </main>\n      <footer className='bg-card h-10 border-t'>\n        <div className='mx-auto size-full max-w-7xl px-4 sm:px-6'>\n          <div className='border-card-foreground/10 h-full bg-[repeating-linear-gradient(45deg,color-mix(in_oklab,var(--card-foreground)10%,transparent),color-mix(in_oklab,var(--card-foreground)10%,transparent)_1px,var(--card)_2px,var(--card)_15px)]' />\n        </div>\n      </footer>\n    </div>\n  )\n}\n\nexport default Header\n",
      "type": "registry:page",
      "target": "app/dashboard-header-10/page.tsx"
    },
    {
      "path": "src/assets/svg/logo.tsx",
      "content": "// React Imports\nimport type { SVGAttributes } from 'react'\n\nconst Logo = (props: SVGAttributes<SVGElement>) => {\n  return (\n    <svg width='1em' height='1em' viewBox='0 0 328 329' fill='none' xmlns='http://www.w3.org/2000/svg' {...props}>\n      <rect y='0.5' width='328' height='328' rx='164' fill='black' className='dark:fill-white' />\n      <path\n        d='M165.018 72.3008V132.771C165.018 152.653 148.9 168.771 129.018 168.771H70.2288'\n        stroke='white'\n        strokeWidth='20'\n        className='dark:stroke-black'\n      />\n      <path\n        d='M166.627 265.241L166.627 204.771C166.627 184.889 182.744 168.771 202.627 168.771L261.416 168.771'\n        stroke='white'\n        strokeWidth='20'\n        className='dark:stroke-black'\n      />\n      <line\n        x1='238.136'\n        y1='98.8184'\n        x2='196.76'\n        y2='139.707'\n        stroke='white'\n        strokeWidth='20'\n        className='dark:stroke-black'\n      />\n      <line\n        x1='135.688'\n        y1='200.957'\n        x2='94.3128'\n        y2='241.845'\n        stroke='white'\n        strokeWidth='20'\n        className='dark:stroke-black'\n      />\n      <line\n        x1='133.689'\n        y1='137.524'\n        x2='92.5566'\n        y2='96.3914'\n        stroke='white'\n        strokeWidth='20'\n        className='dark:stroke-black'\n      />\n      <line\n        x1='237.679'\n        y1='241.803'\n        x2='196.547'\n        y2='200.671'\n        stroke='white'\n        strokeWidth='20'\n        className='dark:stroke-black'\n      />\n    </svg>\n  )\n}\n\nexport default Logo\n",
      "type": "registry:component",
      "target": "assets/svg/logo.tsx"
    },
    {
      "path": "src/registry/new-york/components/blocks/dialog-activity.tsx",
      "content": "import type { ReactNode } from 'react'\n\nimport { ImageIcon } from 'lucide-react'\n\nimport { Badge } from '@/components/ui/badge'\nimport { Input } from '@/components/ui/input'\nimport { Separator } from '@/components/ui/separator'\nimport { Avatar, AvatarFallback, AvatarImage } from '@/components/ui/avatar'\nimport {\n  Sheet,\n  SheetContent,\n  SheetDescription,\n  SheetHeader,\n  SheetTitle,\n  SheetTrigger\n} from '@/components/ui/sheet'\n\ntype Props = {\n  trigger: ReactNode\n  defaultOpen?: boolean\n}\n\nconst ActivityDialog = ({ defaultOpen = false, trigger }: Props) => {\n  return (\n    <Sheet defaultOpen={defaultOpen}>\n      <SheetTrigger asChild>{trigger}</SheetTrigger>\n      <SheetContent className='gap-0 sm:max-w-112 [&>button]:top-2.75 [&>button>svg]:size-5'>\n        <SheetHeader className='border-b py-2.25'>\n          <SheetTitle className='text-lg leading-6'>Activity</SheetTitle>\n          <SheetDescription hidden />\n        </SheetHeader>\n\n        <div className='overflow-y-auto'>\n          <div className='flex gap-4 px-4 py-3'>\n            <Avatar>\n              <AvatarImage src='https://cdn.shadcnstudio.com/ss-assets/avatar/avatar-1.png' />\n              <AvatarFallback>JL</AvatarFallback>\n            </Avatar>\n            <div className='flex w-full flex-col items-start gap-2.5'>\n              <div className='text-muted-foreground flex flex-col items-start text-sm'>\n                <p>\n                  <span className='text-foreground font-semibold'>Joe Lincoln</span> mentioned you in last trends topic\n                </p>\n                <p>18 mins ago</p>\n              </div>\n              <div className='bg-muted flex flex-col gap-4 rounded-md border px-4 py-2.5'>\n                <p className='text-sm font-medium'>\n                  @ShadcnStudio For an expert opinion, check out what Mike has to say on this topic!\n                </p>\n                <div className='relative'>\n                  <Input placeholder='Reply' className='peer bg-card pr-9' />\n                  <div className='text-muted-foreground pointer-events-none absolute inset-y-0 right-0 flex items-center justify-center pr-3 peer-disabled:opacity-50'>\n                    <ImageIcon className='size-4' />\n                    <span className='sr-only'>Email</span>\n                  </div>\n                </div>\n              </div>\n            </div>\n          </div>\n\n          <Separator />\n\n          <div className='flex gap-4 px-4 py-3'>\n            <Avatar>\n              <AvatarImage src='https://cdn.shadcnstudio.com/ss-assets/avatar/avatar-2.png' />\n              <AvatarFallback>JP</AvatarFallback>\n            </Avatar>\n            <div className='flex w-full flex-col items-start gap-2.5'>\n              <div className='text-muted-foreground flex flex-col items-start text-sm'>\n                <p>\n                  <span className='text-foreground font-semibold'>Jane Perez</span> invites you to review a file\n                </p>\n                <p>39 mins ago</p>\n              </div>\n              <div className='bg-muted flex items-center gap-1 rounded-md px-1.5 py-1'>\n                <img\n                  src='https://cdn.shadcnstudio.com/ss-assets/blocks/dashboard-application/dashboard-dialog/image-14.png'\n                  className='h-5'\n                />\n                <span className='text-sm font-medium'>invoices.pdf</span>\n              </div>\n            </div>\n          </div>\n\n          <Separator />\n\n          <div className='flex gap-4 px-4 py-3'>\n            <Avatar>\n              <AvatarImage src='https://cdn.shadcnstudio.com/ss-assets/avatar/avatar-3.png' />\n              <AvatarFallback>TH</AvatarFallback>\n            </Avatar>\n            <div className='flex w-full flex-col items-start gap-2.5'>\n              <div className='text-muted-foreground flex flex-col items-start text-sm'>\n                <p>\n                  <span className='text-foreground font-semibold'>Tyler Hero</span> wants to view your design project\n                </p>\n                <p>1 hour ago</p>\n              </div>\n              <div className='bg-muted flex w-full items-center gap-4 rounded-md border px-4 py-2.5'>\n                <img\n                  src='https://cdn.shadcnstudio.com/ss-assets/blocks/dashboard-application/dashboard-dialog/image-13.png'\n                  className='size-8 rounded-sm'\n                />\n                <span className='text-sm font-medium'>Launcher-Uikit.fig</span>\n              </div>\n            </div>\n          </div>\n\n          <Separator />\n\n          <div className='flex gap-4 px-4 py-3'>\n            <Avatar>\n              <AvatarImage src='https://cdn.shadcnstudio.com/ss-assets/avatar/avatar-5.png' />\n              <AvatarFallback>D</AvatarFallback>\n            </Avatar>\n            <div className='text-muted-foreground flex flex-col items-start text-sm'>\n              <p>\n                <span className='text-foreground font-semibold'>Denial</span> invites you to review the new design\n              </p>\n              <p>3 hours ago</p>\n            </div>\n          </div>\n\n          <Separator />\n\n          <div className='flex gap-4 px-4 py-3'>\n            <Avatar>\n              <AvatarImage src='https://cdn.shadcnstudio.com/ss-assets/avatar/avatar-6.png' />\n              <AvatarFallback>LA</AvatarFallback>\n            </Avatar>\n            <div className='flex w-full flex-col items-start gap-2.5'>\n              <div className='text-muted-foreground flex flex-col items-start text-sm'>\n                <p>\n                  <span className='text-foreground font-semibold'>Leslie Alexander</span> new tags to Web Redesign\n                </p>\n                <p>8 hours ago</p>\n              </div>\n              <div className='flex flex-wrap items-center gap-2'>\n                <Badge className='bg-primary/10 text-primary font-normal'>Client-Request</Badge>\n                <Badge className='bg-sky-600/10 font-normal text-sky-600 dark:bg-sky-400/10 dark:text-sky-400'>\n                  Figma\n                </Badge>\n                <Badge className='bg-amber-600/10 font-normal text-amber-600 dark:bg-amber-400/10 dark:text-amber-400'>\n                  Redesign\n                </Badge>\n              </div>\n            </div>\n          </div>\n\n          <Separator />\n\n          <div className='flex gap-4 px-4 py-3'>\n            <Avatar>\n              <AvatarImage src='https://cdn.shadcnstudio.com/ss-assets/avatar/avatar-8.png' />\n              <AvatarFallback>M</AvatarFallback>\n            </Avatar>\n            <div className='text-muted-foreground flex flex-col items-start text-sm'>\n              <p>\n                <span className='text-foreground font-semibold'>Miya</span> invites you to review a file\n              </p>\n              <p>10 hours ago</p>\n            </div>\n          </div>\n        </div>\n      </SheetContent>\n    </Sheet>\n  )\n}\n\nexport default ActivityDialog\n",
      "type": "registry:component",
      "target": "components/shadcn-studio/blocks/dialog-activity.tsx"
    },
    {
      "path": "src/registry/new-york/components/blocks/dropdown-language.tsx",
      "content": "'use client'\n\nimport { useState } from 'react'\nimport type { ReactNode } from 'react'\n\nimport {\n  DropdownMenu,\n  DropdownMenuContent,\n  DropdownMenuRadioGroup,\n  DropdownMenuRadioItem,\n  DropdownMenuTrigger\n} from '@/components/ui/dropdown-menu'\n\ntype Props = {\n  trigger: ReactNode\n  defaultOpen?: boolean\n  align?: 'start' | 'center' | 'end'\n}\n\nconst LanguageDropdown = ({ defaultOpen, align, trigger }: Props) => {\n  const [language, setLanguage] = useState('english')\n\n  return (\n    <DropdownMenu defaultOpen={defaultOpen}>\n      <DropdownMenuTrigger asChild>{trigger}</DropdownMenuTrigger>\n      <DropdownMenuContent className='w-50' align={align || 'end'}>\n        <DropdownMenuRadioGroup value={language} onValueChange={setLanguage}>\n          <DropdownMenuRadioItem\n            value='english'\n            className='data-[state=checked]:bg-accent data-[state=checked]:text-accent-foreground pl-2 text-base [&>span]:hidden'\n          >\n            English\n          </DropdownMenuRadioItem>\n          <DropdownMenuRadioItem\n            value='german'\n            className='data-[state=checked]:bg-accent data-[state=checked]:text-accent-foreground pl-2 text-base [&>span]:hidden'\n          >\n            Deutsch\n          </DropdownMenuRadioItem>\n          <DropdownMenuRadioItem\n            value='spanish'\n            className='data-[state=checked]:bg-accent data-[state=checked]:text-accent-foreground pl-2 text-base [&>span]:hidden'\n          >\n            Española\n          </DropdownMenuRadioItem>\n          <DropdownMenuRadioItem\n            value='portuguese'\n            className='data-[state=checked]:bg-accent data-[state=checked]:text-accent-foreground pl-2 text-base [&>span]:hidden'\n          >\n            Português\n          </DropdownMenuRadioItem>\n          <DropdownMenuRadioItem\n            value='korean'\n            className='data-[state=checked]:bg-accent data-[state=checked]:text-accent-foreground pl-2 text-base [&>span]:hidden'\n          >\n            한국인\n          </DropdownMenuRadioItem>\n        </DropdownMenuRadioGroup>\n      </DropdownMenuContent>\n    </DropdownMenu>\n  )\n}\n\nexport default LanguageDropdown\n",
      "type": "registry:component",
      "target": "components/shadcn-studio/blocks/dropdown-language.tsx"
    },
    {
      "path": "src/registry/new-york/components/blocks/dropdown-notification.tsx",
      "content": "import type { ReactNode } from 'react'\n\nimport { SettingsIcon, XIcon, LinkIcon } from 'lucide-react'\n\nimport { Badge } from '@/components/ui/badge'\nimport { Button } from '@/components/ui/button'\nimport { Avatar, AvatarImage, AvatarFallback } from '@/components/ui/avatar'\nimport { Tabs, TabsContent, TabsList, TabsTrigger } from '@/components/ui/tabs'\nimport {\n  DropdownMenu,\n  DropdownMenuContent,\n  DropdownMenuLabel,\n  DropdownMenuTrigger,\n  DropdownMenuSeparator,\n  DropdownMenuItem\n} from '@/components/ui/dropdown-menu'\n\ntype Props = {\n  trigger: ReactNode\n  defaultOpen?: boolean\n  align?: 'start' | 'center' | 'end'\n}\n\nconst NotificationDropdown = ({ trigger, defaultOpen, align = 'end' }: Props) => {\n  return (\n    <DropdownMenu defaultOpen={defaultOpen}>\n      <DropdownMenuTrigger asChild>{trigger}</DropdownMenuTrigger>\n      <DropdownMenuContent className='max-w-xs sm:max-w-122' align={align || 'end'}>\n        <Tabs defaultValue='inbox' className='gap-0'>\n          <DropdownMenuLabel className='flex flex-col pb-0'>\n            <div className='flex items-center justify-between gap-6 pb-2.5'>\n              <span className='text-muted-foreground text-base font-normal uppercase'>Notifications</span>\n              <Badge variant='secondary' className='bg-primary/10 text-primary rounded-full font-normal'>\n                8 New\n              </Badge>\n            </div>\n            <div className='-mb-0.5 flex items-center justify-between gap-4'>\n              <TabsList className='relative h-fit rounded-none bg-transparent p-0'>\n                <TabsTrigger\n                  value='inbox'\n                  className='data-[state=active]:!border-b-primary rounded-none border-b-2 border-b-transparent font-normal data-[state=active]:bg-transparent data-[state=active]:shadow-none dark:data-[state=active]:border-transparent dark:data-[state=active]:bg-transparent'\n                >\n                  Inbox\n                </TabsTrigger>\n                <TabsTrigger\n                  value='general'\n                  className='data-[state=active]:!border-b-primary rounded-none border-b-2 border-b-transparent font-normal data-[state=active]:bg-transparent data-[state=active]:shadow-none dark:data-[state=active]:border-transparent dark:data-[state=active]:bg-transparent'\n                >\n                  General\n                </TabsTrigger>\n              </TabsList>\n              <SettingsIcon className='size-5' />\n            </div>\n          </DropdownMenuLabel>\n\n          <DropdownMenuSeparator className='mt-0 h-0.5' />\n\n          <TabsContent value='inbox'>\n            <DropdownMenuItem className='gap-3 px-2 py-3 text-base'>\n              <Avatar className='size-9.5'>\n                <AvatarImage src='https://cdn.shadcnstudio.com/ss-assets/avatar/avatar-19.png' />\n                <AvatarFallback>MB</AvatarFallback>\n              </Avatar>\n              <div className='flex w-full flex-col items-start'>\n                <span className='text-base font-medium'>Mark Bush</span>\n                <div className='flex items-center gap-2.5'>\n                  <span className='text-muted-foreground text-sm'>12 Minutes ago</span>\n                  <div className='bg-muted size-1.5 rounded-full' />\n                  <span className='text-muted-foreground text-sm'>New post</span>\n                </div>\n              </div>\n              <div className='flex flex-col items-center gap-3'>\n                <XIcon className='text-foreground size-3.5' />\n                <div className='bg-primary size-1.5 rounded-full' />\n              </div>\n            </DropdownMenuItem>\n            <DropdownMenuSeparator />\n            <DropdownMenuItem className='gap-3 px-2 py-3 text-base'>\n              <Avatar className='size-9.5'>\n                <AvatarImage src='https://cdn.shadcnstudio.com/ss-assets/avatar/avatar-5.png' />\n                <AvatarFallback>AB</AvatarFallback>\n              </Avatar>\n              <div className='flex w-full flex-col items-start'>\n                <span className='text-base font-medium'>Aaron Black</span>\n                <div className='flex items-center gap-2.5'>\n                  <span className='text-muted-foreground text-sm'>27 Minutes ago</span>\n                  <div className='bg-muted size-1.5 rounded-full' />\n                  <span className='text-muted-foreground text-sm'>New comment</span>\n                </div>\n              </div>\n              <div className='flex flex-col items-center gap-3'>\n                <XIcon className='text-foreground size-3.5' />\n                <div className='bg-primary size-1.5 rounded-full' />\n              </div>\n            </DropdownMenuItem>\n            <DropdownMenuSeparator />\n            <DropdownMenuItem className='items-start gap-3 px-2 py-3 text-base'>\n              <Avatar className='size-9.5'>\n                <AvatarImage src='https://cdn.shadcnstudio.com/ss-assets/avatar/avatar-2.png' />\n                <AvatarFallback>A</AvatarFallback>\n              </Avatar>\n              <div className='flex w-full flex-col items-start'>\n                <span className='text-base font-medium'>Anna has applied to create an ad for your campaign</span>\n                <div className='flex items-center gap-2.5'>\n                  <span className='text-muted-foreground text-sm'>2 hours ago</span>\n                  <div className='bg-muted size-1.5 rounded-full' />\n                  <span className='text-muted-foreground text-sm'>New request for campaign</span>\n                </div>\n                <div className='mt-3 flex items-center gap-4'>\n                  <Button variant='secondary' size='sm'>\n                    Decline\n                  </Button>\n                  <Button size='sm'>Accept</Button>\n                </div>\n              </div>\n            </DropdownMenuItem>\n            <DropdownMenuSeparator />\n            <DropdownMenuItem className='items-start gap-3 px-2 py-3 text-base'>\n              <Avatar className='size-9.5'>\n                <AvatarImage src='https://cdn.shadcnstudio.com/ss-assets/avatar/avatar-3.png' />\n                <AvatarFallback>J</AvatarFallback>\n              </Avatar>\n              <div className='flex w-full flex-col items-start'>\n                <span className='text-base font-medium'>Jason attached the file</span>\n                <div className='flex items-center gap-2.5'>\n                  <span className='text-muted-foreground text-sm'>6 hours ago</span>\n                  <div className='bg-muted size-1.5 rounded-full' />\n                  <span className='text-muted-foreground text-sm'>Attached files</span>\n                </div>\n                <div className='mt-3 flex items-center gap-1.5'>\n                  <LinkIcon className='text-foreground' />\n                  <span className='text-sm'>Work examples.com</span>\n                </div>\n              </div>\n            </DropdownMenuItem>\n          </TabsContent>\n\n          <TabsContent value='general'>\n            <DropdownMenuItem className='gap-3 px-2 py-3 text-base'>\n              <Avatar className='size-9.5'>\n                <AvatarImage src='https://cdn.shadcnstudio.com/ss-assets/avatar/avatar-7.png' />\n                <AvatarFallback>FC</AvatarFallback>\n              </Avatar>\n              <div className='flex w-full flex-col items-start'>\n                <span className='text-base font-medium'>Fred Campbell</span>\n                <div className='flex items-center gap-2.5'>\n                  <span className='text-muted-foreground text-sm'>39 Minutes ago</span>\n                  <div className='bg-muted size-1.5 rounded-full' />\n                  <span className='text-muted-foreground text-sm'>New comment</span>\n                </div>\n              </div>\n              <div className='flex flex-col items-center gap-3'>\n                <XIcon className='text-foreground size-3.5' />\n                <div className='bg-primary size-1.5 rounded-full' />\n              </div>\n            </DropdownMenuItem>\n            <DropdownMenuSeparator />\n            <DropdownMenuItem className='items-start gap-3 px-2 py-3 text-base'>\n              <Avatar className='size-9.5'>\n                <AvatarImage src='https://cdn.shadcnstudio.com/ss-assets/avatar/avatar-15.png' />\n                <AvatarFallback>S</AvatarFallback>\n              </Avatar>\n              <div className='flex w-full flex-col items-start'>\n                <span className='text-base font-medium'>Scott attached the file</span>\n                <div className='flex items-center gap-2.5'>\n                  <span className='text-muted-foreground text-sm'>3 hours ago</span>\n                  <div className='bg-muted size-1.5 rounded-full' />\n                  <span className='text-muted-foreground text-sm'>Attached files</span>\n                </div>\n                <div className='mt-3 flex items-center gap-1.5'>\n                  <LinkIcon className='text-foreground' />\n                  <span className='text-sm'>Work examples.com</span>\n                </div>\n              </div>\n            </DropdownMenuItem>\n            <DropdownMenuSeparator />\n            <DropdownMenuItem className='gap-3 px-2 py-3 text-base'>\n              <Avatar className='size-9.5'>\n                <AvatarImage src='https://cdn.shadcnstudio.com/ss-assets/avatar/avatar-11.png' />\n                <AvatarFallback>HL</AvatarFallback>\n              </Avatar>\n              <div className='flex w-full flex-col items-start'>\n                <span className='text-base font-medium'>Harold Larson</span>\n                <div className='flex items-center gap-2.5'>\n                  <span className='text-muted-foreground text-sm'>5 hours ago</span>\n                  <div className='bg-muted size-1.5 rounded-full' />\n                  <span className='text-muted-foreground text-sm'>New post</span>\n                </div>\n              </div>\n              <div className='flex flex-col items-center gap-3'>\n                <XIcon className='text-foreground size-3.5' />\n                <div className='bg-primary size-1.5 rounded-full' />\n              </div>\n            </DropdownMenuItem>\n            <DropdownMenuSeparator />\n            <DropdownMenuItem className='items-start gap-3 px-2 py-3 text-base'>\n              <Avatar className='size-9.5'>\n                <AvatarImage src='https://cdn.shadcnstudio.com/ss-assets/avatar/avatar-6.png' />\n                <AvatarFallback>R</AvatarFallback>\n              </Avatar>\n              <div className='flex w-full flex-col items-start'>\n                <span className='text-base font-medium'>Rosie has applied to create an ad for your campaign</span>\n                <div className='flex items-center gap-2.5'>\n                  <span className='text-muted-foreground text-sm'>8 hours ago</span>\n                  <div className='bg-muted size-1.5 rounded-full' />\n                  <span className='text-muted-foreground text-sm'>New request for campaign</span>\n                </div>\n                <div className='mt-3 flex items-center gap-4'>\n                  <Button variant='secondary' size='sm'>\n                    Decline\n                  </Button>\n                  <Button size='sm'>Accept</Button>\n                </div>\n              </div>\n            </DropdownMenuItem>\n          </TabsContent>\n        </Tabs>\n      </DropdownMenuContent>\n    </DropdownMenu>\n  )\n}\n\nexport default NotificationDropdown\n",
      "type": "registry:component",
      "target": "components/shadcn-studio/blocks/dropdown-notification.tsx"
    },
    {
      "path": "src/registry/new-york/components/blocks/dropdown-profile.tsx",
      "content": "import type { ReactNode } from 'react'\n\nimport {\n  UserIcon,\n  SettingsIcon,\n  CreditCardIcon,\n  UsersIcon,\n  SquarePenIcon,\n  CirclePlusIcon,\n  LogOutIcon\n} from 'lucide-react'\n\nimport { Avatar, AvatarImage, AvatarFallback } from '@/components/ui/avatar'\nimport {\n  DropdownMenu,\n  DropdownMenuContent,\n  DropdownMenuGroup,\n  DropdownMenuItem,\n  DropdownMenuLabel,\n  DropdownMenuSeparator,\n  DropdownMenuTrigger\n} from '@/components/ui/dropdown-menu'\n\ntype Props = {\n  trigger: ReactNode\n  defaultOpen?: boolean\n  align?: 'start' | 'center' | 'end'\n}\n\nconst ProfileDropdown = ({ trigger, defaultOpen, align = 'end' }: Props) => {\n  return (\n    <DropdownMenu defaultOpen={defaultOpen}>\n      <DropdownMenuTrigger asChild>{trigger}</DropdownMenuTrigger>\n      <DropdownMenuContent className='w-80' align={align || 'end'}>\n        <DropdownMenuLabel className='flex items-center gap-4 px-4 py-2.5 font-normal'>\n          <div className='relative'>\n            <Avatar className='size-10'>\n              <AvatarImage src='https://cdn.shadcnstudio.com/ss-assets/avatar/avatar-1.png' alt='John Doe' />\n              <AvatarFallback>JD</AvatarFallback>\n            </Avatar>\n            <span className='ring-card absolute right-0 bottom-0 block size-2 rounded-full bg-green-600 ring-2' />\n          </div>\n          <div className='flex flex-1 flex-col items-start'>\n            <span className='text-foreground text-lg font-semibold'>John Doe</span>\n            <span className='text-muted-foreground text-base'>john.doe@example.com</span>\n          </div>\n        </DropdownMenuLabel>\n\n        <DropdownMenuSeparator />\n\n        <DropdownMenuGroup>\n          <DropdownMenuItem className='px-4 py-2.5 text-base'>\n            <UserIcon className='text-foreground size-5' />\n            <span>My account</span>\n          </DropdownMenuItem>\n          <DropdownMenuItem className='px-4 py-2.5 text-base'>\n            <SettingsIcon className='text-foreground size-5' />\n            <span>Settings</span>\n          </DropdownMenuItem>\n          <DropdownMenuItem className='px-4 py-2.5 text-base'>\n            <CreditCardIcon className='text-foreground size-5' />\n            <span>Billing</span>\n          </DropdownMenuItem>\n        </DropdownMenuGroup>\n\n        <DropdownMenuSeparator />\n\n        <DropdownMenuGroup>\n          <DropdownMenuItem className='px-4 py-2.5 text-base'>\n            <UsersIcon className='text-foreground size-5' />\n            <span>Manage team</span>\n          </DropdownMenuItem>\n          <DropdownMenuItem className='px-4 py-2.5 text-base'>\n            <SquarePenIcon className='text-foreground size-5' />\n            <span>Customization</span>\n          </DropdownMenuItem>\n          <DropdownMenuItem className='px-4 py-2.5 text-base'>\n            <CirclePlusIcon className='text-foreground size-5' />\n            <span>Add team account</span>\n          </DropdownMenuItem>\n        </DropdownMenuGroup>\n\n        <DropdownMenuSeparator />\n\n        <DropdownMenuItem variant='destructive' className='px-4 py-2.5 text-base'>\n          <LogOutIcon className='size-5' />\n          <span>Logout</span>\n        </DropdownMenuItem>\n      </DropdownMenuContent>\n    </DropdownMenu>\n  )\n}\n\nexport default ProfileDropdown\n",
      "type": "registry:component",
      "target": "components/shadcn-studio/blocks/dropdown-profile.tsx"
    },
    {
      "path": "src/registry/new-york/components/blocks/menu-dropdown.tsx",
      "content": "'use client'\n\nimport type { ReactNode } from 'react'\n\nimport { ChevronRightIcon, CircleSmallIcon } from 'lucide-react'\n\nimport { Collapsible, CollapsibleContent, CollapsibleTrigger } from '@/components/ui/collapsible'\nimport {\n  DropdownMenu,\n  DropdownMenuContent,\n  DropdownMenuGroup,\n  DropdownMenuItem,\n  DropdownMenuTrigger\n} from '@/components/ui/dropdown-menu'\n\nexport type NavigationItem = {\n  title: string\n  href: string\n}\n\nexport type NavigationSection = {\n  title: string\n  icon?: ReactNode\n} & (\n  | {\n      items: NavigationItem[]\n      href?: never\n    }\n  | {\n      items?: never\n      href: string\n    }\n)\n\ntype Props = {\n  trigger: ReactNode\n  navigationData: NavigationSection[]\n  align?: 'center' | 'end' | 'start'\n}\n\nconst MenuDropdown = ({ trigger, navigationData, align = 'start' }: Props) => {\n  return (\n    <DropdownMenu>\n      <DropdownMenuTrigger asChild>{trigger}</DropdownMenuTrigger>\n      <DropdownMenuContent className='w-56' align={align}>\n        {navigationData.map(navItem => {\n          if (navItem.href) {\n            return (\n              <DropdownMenuItem key={navItem.title} asChild>\n                <a href={navItem.href}>\n                  {navItem.icon}\n                  {navItem.title}\n                </a>\n              </DropdownMenuItem>\n            )\n          }\n\n          return (\n            <Collapsible key={navItem.title} asChild>\n              <DropdownMenuGroup>\n                <CollapsibleTrigger asChild>\n                  <DropdownMenuItem onSelect={event => event.preventDefault()} className='justify-between'>\n                    {navItem.icon}\n                    <span className='flex-1'>{navItem.title}</span>\n                    <ChevronRightIcon className='shrink-0 transition-transform [[data-state=\"open\"]>&]:rotate-90' />\n                  </DropdownMenuItem>\n                </CollapsibleTrigger>\n                <CollapsibleContent className='pl-2'>\n                  {navItem.items?.map(item => (\n                    <DropdownMenuItem key={item.title} asChild>\n                      <a href={item.href}>\n                        <CircleSmallIcon />\n                        <span>{item.title}</span>\n                      </a>\n                    </DropdownMenuItem>\n                  ))}\n                </CollapsibleContent>\n              </DropdownMenuGroup>\n            </Collapsible>\n          )\n        })}\n      </DropdownMenuContent>\n    </DropdownMenu>\n  )\n}\n\nexport default MenuDropdown\n",
      "type": "registry:component",
      "target": "components/shadcn-studio/blocks/menu-dropdown.tsx"
    }
  ]
}