{
  "$schema": "https://ui.shadcn.com/schema/registry-item.json",
  "name": "dashboard-dropdown-08",
  "type": "registry:block",
  "description": "An advanced user dropdown with motion animations, toggle groups, badges, switches, and interactive elements for enhanced user experience.",
  "dependencies": [
    "@radix-ui/react-toggle-group",
    "class-variance-authority",
    "lucide-react",
    "motion"
  ],
  "registryDependencies": [
    "avatar",
    "badge",
    "button",
    "dropdown-menu",
    "switch",
    "toggle-group",
    "utils"
  ],
  "files": [
    {
      "path": "src/registry/new-york/blocks/dashboard-and-application/dashboard-dropdown/dashboard-dropdown-08/page.tsx",
      "content": "import { Avatar, AvatarImage, AvatarFallback } from '@/components/ui/avatar'\n\nimport UserDropdown from '@/components/shadcn-studio/blocks/dashboard-dropdown-08/user-dropdown'\n\nconst DropdownPage = () => {\n  return (\n    <div className='flex h-167 items-start justify-center p-8'>\n      <UserDropdown\n        defaultOpen\n        align='center'\n        trigger={\n          <Avatar className='size-10 cursor-pointer'>\n            <AvatarImage src='https://cdn.shadcnstudio.com/ss-assets/avatar/avatar-1.png' alt='John Doe' />\n            <AvatarFallback>JD</AvatarFallback>\n          </Avatar>\n        }\n      />\n    </div>\n  )\n}\n\nexport default DropdownPage\n",
      "type": "registry:page",
      "target": "app/dashboard-dropdown-08/page.tsx"
    },
    {
      "path": "src/registry/new-york/components/blocks/dashboard-dropdown-08/user-dropdown.tsx",
      "content": "'use client'\n\nimport { useState, type ReactNode } from 'react'\n\nimport {\n  BookIcon,\n  ChartPieIcon,\n  InfoIcon,\n  LaptopMinimalIcon,\n  LayoutGridIcon,\n  LogOutIcon,\n  MoonIcon,\n  SettingsIcon,\n  SunMediumIcon,\n  UserIcon\n} from 'lucide-react'\n\nimport { Avatar, AvatarImage, AvatarFallback } from '@/components/ui/avatar'\nimport { Button } from '@/components/ui/button'\nimport {\n  DropdownMenu,\n  DropdownMenuContent,\n  DropdownMenuGroup,\n  DropdownMenuItem,\n  DropdownMenuLabel,\n  DropdownMenuSeparator,\n  DropdownMenuTrigger\n} from '@/components/ui/dropdown-menu'\nimport { ToggleGroup, ToggleGroupItem } from '@/components/ui/motion-toggle-group'\n\ntype Props = {\n  trigger: ReactNode\n  defaultOpen?: boolean\n  align?: 'start' | 'center' | 'end'\n}\n\nconst UserDropdown = ({ trigger, defaultOpen, align = 'end' }: Props) => {\n  const [mode, setMode] = useState<'light' | 'dark' | 'system'>('light')\n\n  return (\n    <DropdownMenu defaultOpen={defaultOpen}>\n      <DropdownMenuTrigger asChild>{trigger}</DropdownMenuTrigger>\n      <DropdownMenuContent className='w-74.5 space-y-1' align={align || 'end'}>\n        <DropdownMenuLabel className='flex items-center gap-4 px-4 py-2.5 font-normal'>\n          <Avatar className='size-10'>\n            <AvatarImage src='https://cdn.shadcnstudio.com/ss-assets/avatar/avatar-1.png' alt='John Doe' />\n            <AvatarFallback>JD</AvatarFallback>\n          </Avatar>\n          <div className='flex flex-1 flex-col items-start gap-0.5'>\n            <span className='text-foreground text-lg font-semibold'>John Doe</span>\n            <span className='text-muted-foreground text-base'>john.doe@example.com</span>\n          </div>\n        </DropdownMenuLabel>\n\n        <DropdownMenuSeparator />\n\n        <DropdownMenuGroup className='space-y-0.5'>\n          <DropdownMenuItem className='px-4 py-2.5 text-base'>\n            <UserIcon className='text-foreground size-5' />\n            <span>My account</span>\n          </DropdownMenuItem>\n          <DropdownMenuItem className='px-4 py-2.5 text-base'>\n            <LayoutGridIcon className='text-foreground size-5' />\n            <span>Feed</span>\n          </DropdownMenuItem>\n          <DropdownMenuItem className='px-4 py-2.5 text-base'>\n            <SettingsIcon className='text-foreground size-5' />\n            <span>Account Settings</span>\n          </DropdownMenuItem>\n          <DropdownMenuItem className='px-4 py-2.5 text-base'>\n            <ChartPieIcon className='text-foreground size-5' />\n            <span>Analytics</span>\n          </DropdownMenuItem>\n          <DropdownMenuItem className='px-4 py-2.5 text-base'>\n            <BookIcon className='text-foreground size-5' />\n            <span>Guide</span>\n          </DropdownMenuItem>\n          <DropdownMenuItem className='px-4 py-2.5 text-base'>\n            <InfoIcon className='text-foreground size-5' />\n            <span>Help Center</span>\n          </DropdownMenuItem>\n          <DropdownMenuItem\n            className='justify-between px-4 py-2.5 text-base'\n            onSelect={event => event.preventDefault()}\n          >\n            <span>Theme</span>\n            <ToggleGroup type='single' defaultValue={mode} className='bg-primary/10 overflow-hidden rounded-full p-0.5'>\n              <ToggleGroupItem\n                value='light'\n                aria-label='Toggle light'\n                className='h-7 min-w-7 px-1'\n                buttonProps={{\n                  className:\n                    'aria-[checked=true]:[&_[data-slot=active-toggle-group-item]]:bg-background text-foreground [&_[data-slot=active-toggle-group-item]]:!rounded-full'\n                }}\n                onClick={() => setMode('light')}\n              >\n                <SunMediumIcon className='text-primary size-4' />\n              </ToggleGroupItem>\n              <ToggleGroupItem\n                value='dark'\n                aria-label='Toggle dark'\n                className='h-7 min-w-7 px-1'\n                buttonProps={{\n                  className:\n                    'aria-[checked=true]:[&_[data-slot=active-toggle-group-item]]:bg-background text-foreground [&_[data-slot=active-toggle-group-item]]:!rounded-full'\n                }}\n                onClick={() => setMode('dark')}\n              >\n                <MoonIcon className='text-primary size-4' />\n              </ToggleGroupItem>\n              <ToggleGroupItem\n                value='system'\n                aria-label='Toggle system'\n                className='h-7 min-w-7 px-1'\n                buttonProps={{\n                  className:\n                    'aria-[checked=true]:[&_[data-slot=active-toggle-group-item]]:bg-background text-foreground [&_[data-slot=active-toggle-group-item]]:!rounded-full'\n                }}\n                onClick={() => setMode('system')}\n              >\n                <LaptopMinimalIcon className='text-primary size-4' />\n              </ToggleGroupItem>\n            </ToggleGroup>\n          </DropdownMenuItem>\n        </DropdownMenuGroup>\n\n        <DropdownMenuSeparator />\n\n        <DropdownMenuGroup>\n          <DropdownMenuItem className='justify-between gap-2 rounded-md px-4 py-2.5 text-base'>\n            <div className='flex flex-col gap-0.5'>\n              <span>Free Plan</span>\n              <span className='text-muted-foreground'>13200 Views</span>\n            </div>\n            <Button size='sm' className='bg-primary/10 text-primary hover:bg-primary/20'>\n              Upgrade\n            </Button>\n          </DropdownMenuItem>\n        </DropdownMenuGroup>\n\n        <DropdownMenuSeparator />\n\n        <DropdownMenuGroup>\n          <DropdownMenuItem variant='destructive' className='px-4 py-2.5 text-base'>\n            <LogOutIcon className='size-5' />\n            <span>Sign out</span>\n          </DropdownMenuItem>\n        </DropdownMenuGroup>\n      </DropdownMenuContent>\n    </DropdownMenu>\n  )\n}\n\nexport default UserDropdown\n",
      "type": "registry:component",
      "target": "components/shadcn-studio/blocks/dashboard-dropdown-08/user-dropdown.tsx"
    },
    {
      "path": "src/registry/new-york/ui/motion-toggle-group.tsx",
      "content": "'use client'\n\nimport * as React from 'react'\n\nimport * as ToggleGroupPrimitive from '@radix-ui/react-toggle-group'\nimport { type HTMLMotionProps, type Transition, motion, AnimatePresence } from 'motion/react'\nimport { cva, type VariantProps } from 'class-variance-authority'\n\nimport { cn } from '@/lib/utils'\n\nconst toggleVariants = cva(\n  \"hover:text-muted-foreground text-accent-foreground data-[state=on]:text-accent-foreground focus-visible:border-ring focus-visible:ring-ring/50 aria-invalid:ring-destructive/20 dark:aria-invalid:ring-destructive/40 aria-invalid:border-destructive inline-flex cursor-pointer items-center justify-center gap-2 rounded-md text-sm font-medium whitespace-nowrap transition-[color,box-shadow] outline-none focus:outline-none focus-visible:ring-[3px] disabled:pointer-events-none disabled:opacity-50 [&_svg]:pointer-events-none [&_svg]:shrink-0 [&_svg:not([class*='size-'])]:size-4\",\n  {\n    variants: {\n      type: {\n        single: '',\n        multiple: 'data-[state=on]:bg-accent'\n      },\n      variant: {\n        default: 'bg-transparent',\n        outline: 'border-input border bg-transparent shadow-xs'\n      },\n      size: {\n        default: 'h-9 min-w-9 px-2',\n        sm: 'h-8 min-w-8 px-1.5',\n        lg: 'h-10 min-w-10 px-2.5'\n      }\n    },\n    defaultVariants: {\n      variant: 'default',\n      size: 'default'\n    }\n  }\n)\n\ntype ToggleGroupContextProps = VariantProps<typeof toggleVariants> & {\n  type?: 'single' | 'multiple'\n  transition?: Transition\n  activeClassName?: string\n  globalId: string\n}\n\nconst ToggleGroupContext = React.createContext<ToggleGroupContextProps | undefined>(undefined)\n\nconst useToggleGroup = (): ToggleGroupContextProps => {\n  const context = React.useContext(ToggleGroupContext)\n\n  if (!context) {\n    throw new Error('useToggleGroup must be used within a ToggleGroup')\n  }\n\n  return context\n}\n\ntype ToggleGroupProps = React.ComponentProps<typeof ToggleGroupPrimitive.Root> &\n  Omit<VariantProps<typeof toggleVariants>, 'type'> & {\n    transition?: Transition\n    activeClassName?: string\n  }\n\nfunction ToggleGroup({\n  className,\n  variant,\n  size,\n  children,\n  transition = { type: 'spring', bounce: 0, stiffness: 200, damping: 25 },\n  activeClassName,\n  ...props\n}: ToggleGroupProps) {\n  const globalId = React.useId()\n\n  return (\n    <ToggleGroupContext.Provider\n      value={{\n        variant,\n        size,\n        type: props.type,\n        transition,\n        activeClassName,\n        globalId\n      }}\n    >\n      <ToggleGroupPrimitive.Root\n        data-slot='toggle-group'\n        className={cn('relative flex items-center justify-center gap-1', className)}\n        {...props}\n      >\n        {children}\n      </ToggleGroupPrimitive.Root>\n    </ToggleGroupContext.Provider>\n  )\n}\n\ntype ToggleGroupItemProps = React.ComponentProps<typeof ToggleGroupPrimitive.Item> &\n  Omit<VariantProps<typeof toggleVariants>, 'type'> & {\n    children?: React.ReactNode\n    buttonProps?: HTMLMotionProps<'button'>\n    spanProps?: React.ComponentProps<'span'>\n  }\n\nfunction ToggleGroupItem({\n  ref,\n  className,\n  children,\n  variant,\n  size,\n  buttonProps,\n  spanProps,\n  ...props\n}: ToggleGroupItemProps) {\n  const { activeClassName, transition, type, variant: contextVariant, size: contextSize, globalId } = useToggleGroup()\n  const itemRef = React.useRef<HTMLButtonElement | null>(null)\n\n  React.useImperativeHandle(ref, () => itemRef.current as HTMLButtonElement)\n  const [isActive, setIsActive] = React.useState(false)\n\n  React.useEffect(() => {\n    const node = itemRef.current\n\n    if (!node) return\n\n    const observer = new MutationObserver(() => {\n      setIsActive(node.getAttribute('data-state') === 'on')\n    })\n\n    observer.observe(node, {\n      attributes: true,\n      attributeFilter: ['data-state']\n    })\n    setIsActive(node.getAttribute('data-state') === 'on')\n\n    return () => observer.disconnect()\n  }, [])\n\n  return (\n    <ToggleGroupPrimitive.Item ref={itemRef} {...props} asChild>\n      <motion.button\n        data-slot='toggle-group-item'\n        initial={{ scale: 1 }}\n        whileTap={{ scale: 0.9 }}\n        {...buttonProps}\n        className={cn('relative', buttonProps?.className)}\n      >\n        <span\n          {...spanProps}\n          data-state={isActive ? 'on' : 'off'}\n          className={cn(\n            'relative z-[1]',\n            toggleVariants({\n              variant: variant || contextVariant,\n              size: size || contextSize,\n              type\n            }),\n            className,\n            spanProps?.className\n          )}\n        >\n          {children}\n        </span>\n\n        <AnimatePresence initial={false}>\n          {isActive && type === 'single' && (\n            <motion.span\n              layoutId={`active-toggle-group-item-${globalId}`}\n              data-slot='active-toggle-group-item'\n              initial={{ opacity: 0 }}\n              animate={{ opacity: 1 }}\n              exit={{ opacity: 0 }}\n              transition={transition}\n              className={cn('bg-muted absolute inset-0 z-0 rounded-md', activeClassName)}\n            />\n          )}\n        </AnimatePresence>\n      </motion.button>\n    </ToggleGroupPrimitive.Item>\n  )\n}\n\nexport { ToggleGroup, ToggleGroupItem, type ToggleGroupProps, type ToggleGroupItemProps }\n",
      "type": "registry:component",
      "target": "components/ui/motion-toggle-group.tsx"
    }
  ]
}